{
	"$schema": "http://schema.management.azure.com/schemas/2015-01-01/deploymentTemplate.json#",
	"contentVersion": "1.0.0.0",
	"parameters": {
		"factoryName": {
			"type": "string",
			"metadata": "Data Factory name",
			"defaultValue": "wendyadf"
		},
		"blob_connectionString": {
			"type": "secureString",
			"metadata": "Secure string for 'connectionString' of 'blob'"
		},
		"gen2_accountKey": {
			"type": "secureString",
			"metadata": "Secure string for 'accountKey' of 'gen2'"
		},
		"gen2_properties_typeProperties_url": {
			"type": "string",
			"defaultValue": "https://wendysawithgen2.dfs.core.windows.net/"
		}
	},
	"variables": {
		"factoryId": "[concat('Microsoft.DataFactory/factories/', parameters('factoryName'))]"
	},
	"resources": [
		{
			"name": "[concat(parameters('factoryName'), '/pipeline1')]",
			"type": "Microsoft.DataFactory/factories/pipelines",
			"apiVersion": "2018-06-01",
			"properties": {
				"activities": [
					{
						"name": "dataflow1",
						"type": "ExecuteDataFlow",
						"dependsOn": [],
						"policy": {
							"timeout": "0.12:00:00",
							"retry": 0,
							"retryIntervalInSeconds": 30,
							"secureOutput": false,
							"secureInput": false
						},
						"userProperties": [],
						"typeProperties": {
							"dataflow": {
								"referenceName": "dataflow1",
								"type": "DataFlowReference",
								"parameters": {},
								"datasetParameters": {
									"source1": {},
									"sink1": {}
								}
							},
							"staging": {},
							"compute": {
								"coreCount": 8,
								"computeType": "General"
							},
							"traceLevel": "Fine"
						}
					}
				],
				"policy": {
					"elapsedTimeMetric": {}
				},
				"annotations": []
			},
			"dependsOn": [
				"[concat(variables('factoryId'), '/dataflows/dataflow1')]"
			]
		},
		{
			"name": "[concat(parameters('factoryName'), '/data_input')]",
			"type": "Microsoft.DataFactory/factories/datasets",
			"apiVersion": "2018-06-01",
			"properties": {
				"linkedServiceName": {
					"referenceName": "blob",
					"type": "LinkedServiceReference"
				},
				"annotations": [],
				"type": "DelimitedText",
				"typeProperties": {
					"location": {
						"type": "AzureBlobStorageLocation",
						"fileName": "moviesDB.csv",
						"container": "con1"
					},
					"columnDelimiter": ",",
					"escapeChar": "\\",
					"firstRowAsHeader": true,
					"quoteChar": "\""
				},
				"schema": [
					{
						"name": "movie",
						"type": "String"
					},
					{
						"name": "title",
						"type": "String"
					},
					{
						"name": "genres",
						"type": "String"
					},
					{
						"name": "year",
						"type": "String"
					},
					{
						"name": "Rating",
						"type": "String"
					},
					{
						"name": "Rotton Tomato",
						"type": "String"
					}
				]
			},
			"dependsOn": [
				"[concat(variables('factoryId'), '/linkedServices/blob')]"
			]
		},
		{
			"name": "[concat(parameters('factoryName'), '/data_output')]",
			"type": "Microsoft.DataFactory/factories/datasets",
			"apiVersion": "2018-06-01",
			"properties": {
				"linkedServiceName": {
					"referenceName": "gen2",
					"type": "LinkedServiceReference"
				},
				"annotations": [],
				"type": "DelimitedText",
				"typeProperties": {
					"location": {
						"type": "AzureBlobFSLocation",
						"fileSystem": "con2"
					},
					"columnDelimiter": ",",
					"escapeChar": "\\",
					"firstRowAsHeader": true,
					"quoteChar": "\""
				},
				"schema": []
			},
			"dependsOn": [
				"[concat(variables('factoryId'), '/linkedServices/gen2')]"
			]
		},
		{
			"name": "[concat(parameters('factoryName'), '/blob')]",
			"type": "Microsoft.DataFactory/factories/linkedServices",
			"apiVersion": "2018-06-01",
			"properties": {
				"annotations": [],
				"type": "AzureBlobStorage",
				"typeProperties": {
					"connectionString": "[parameters('blob_connectionString')]"
				}
			},
			"dependsOn": []
		},
		{
			"name": "[concat(parameters('factoryName'), '/gen2')]",
			"type": "Microsoft.DataFactory/factories/linkedServices",
			"apiVersion": "2018-06-01",
			"properties": {
				"annotations": [],
				"type": "AzureBlobFS",
				"typeProperties": {
					"url": "[parameters('gen2_properties_typeProperties_url')]",
					"accountKey": {
						"type": "SecureString",
						"value": "[parameters('gen2_accountKey')]"
					}
				}
			},
			"dependsOn": []
		},
		{
			"name": "[concat(parameters('factoryName'), '/dataflow1')]",
			"type": "Microsoft.DataFactory/factories/dataflows",
			"apiVersion": "2018-06-01",
			"properties": {
				"type": "MappingDataFlow",
				"typeProperties": {
					"sources": [
						{
							"dataset": {
								"referenceName": "data_input",
								"type": "DatasetReference"
							},
							"name": "source1"
						}
					],
					"sinks": [
						{
							"dataset": {
								"referenceName": "data_output",
								"type": "DatasetReference"
							},
							"name": "sink1"
						}
					],
					"transformations": [
						{
							"name": "filter1"
						}
					],
					"scriptLines": [
						"source(output(",
						"          movie as string,",
						"          title as string,",
						"          genres as string,",
						"          year as string,",
						"          Rating as string,",
						"          {Rotton Tomato} as string",
						"     ),",
						"     allowSchemaDrift: true,",
						"     validateSchema: false,",
						"     ignoreNoFilesFound: false) ~> source1",
						"source1 filter(toInteger(year) >= 1910) ~> filter1",
						"filter1 sink(allowSchemaDrift: true,",
						"     validateSchema: false,",
						"     umask: 0022,",
						"     preCommands: [],",
						"     postCommands: [],",
						"     skipDuplicateMapInputs: true,",
						"     skipDuplicateMapOutputs: true) ~> sink1"
					]
				}
			},
			"dependsOn": [
				"[concat(variables('factoryId'), '/datasets/data_input')]",
				"[concat(variables('factoryId'), '/datasets/data_output')]"
			]
		}
	]
}